texttoknowledge/__init__.py
texttoknowledge/main.py
texttoknowledge/prompts.py
texttoknowledge-2025.12.21231444.dist-info/METADATA
texttoknowledge-2025.12.21231444.dist-info/WHEEL
texttoknowledge-2025.12.21231444.dist-info/top_level.txt
texttoknowledge-2025.12.21231444.dist-info/RECORD
