Metadata-Version: 2.4
Name: texttoknowledge
Version: 2025.12.21231444
Summary: Convert unstructured text into structured, queryable knowledge with llmatch-messages. Extract and organize key details for fast, reliable access—ideal for teams and researchers.
Author-email: texttoknowledge <hi@eugene.plus>
License: MIT
Project-URL: Homepage, https://github.com/chigwell/texttoknowledge
Requires-Python: >=3.9
Requires-Dist: langchain-llm7>=0.0.0
Requires-Dist: llmatch-messages>=0.0.0
Requires-Dist: langchain-core>=0.3.0
